danbot_api/__init__.py
danbot_api/client.py
danbot_api/errors.py
danbot_api/helpers.py
danbot_api/http.py
danbot_hosting_py-1.0.dist-info/LICENSE
danbot_hosting_py-1.0.dist-info/METADATA
danbot_hosting_py-1.0.dist-info/WHEEL
danbot_hosting_py-1.0.dist-info/top_level.txt
danbot_hosting_py-1.0.dist-info/RECORD
