Metadata-Version: 2.1
Name: danbot-hosting-py
Version: 1.0
Summary: A Python Wrapper for the DanBotHosting API
Home-page: https://github.com/Makiyu-py/danbot-hosting
Author: Makiyu
Author-email: 73825066+Makiyu-py@users.noreply.github.com
License: MIT License
Project-URL: Issue tracker, https://github.com/Makiyu-py/danbot-hosting/issues
Keywords: DanBotHosting discord dbh
Platform: UNKNOWN
Classifier: Development Status :: 4 - Beta
Classifier: Intended Audience :: Developers
Classifier: Natural Language :: English
Classifier: License :: OSI Approved :: MIT License
Classifier: Topic :: Internet
Classifier: Topic :: Software Development :: Libraries
Classifier: Topic :: Software Development :: Libraries :: Python Modules
Classifier: Topic :: Utilities
Requires-Python: >=3.6
Requires-Dist: discord.py
